{"id":111302,"xmlId":"io.github.mishkun.ideavimsneak","name":"IdeaVim-Sneak","description":"\n    <h2>\n    Port of <a href=\"https://github.com/justinmk/vim-sneak\">vim-sneak</a> – vim's missing motion to ideavim.\n    </h2>\n\n    <p>\n    It helps you navigate in line effortlessly.\n    In short, it is like `f` and `F`, but accepting two characters instead of one. It makes your movement at least 1000%\n    more precise and accurate.\n    </p>\n\n    <h3>Usage</h3>\n    <p>Add `set sneak` to your ./ideavimrc file for activation</p>\n\n    <ul>\n    <li>Use `s` plus two characters to search forward in document</li>\n    <li>Use `S` plus two characters to search backward in document</li>\n    <li>Use `;` and `,` just as with `f` and `F` commands to repeat searches</li>\n    </ul>\n\n    <h3>Advanced</h3>\n    <p>Plugin respects `set ignorecase` and `set smartcase` settings</p>\n    ","tags":["Editor"],"vendor":"Mishkun","version":"1.2.0","notes":"\n        Thanks to @MunsterPlop for adding support for `set ignorecase` and `set smartcase` in this release!\n      ","dependencies":["com.intellij.modules.platform","IdeaVIM"],"since":"201.0","sourceCodeUrl":"https://github.com/Mishkun/ideavim-sneak","size":1576328}